ciso_genai/__init__.py
ciso_genai/causal_engine.py
ciso_genai/policies.py
ciso_genai/synergy_engine.py
ciso_genai/topology_engine.py
ciso_genai/envs/__init__.py
ciso_genai/envs/gridworld.py
ciso_genai-0.0.2.dist-info/licenses/LICENSE
ciso_genai-0.0.2.dist-info/METADATA
ciso_genai-0.0.2.dist-info/WHEEL
ciso_genai-0.0.2.dist-info/top_level.txt
ciso_genai-0.0.2.dist-info/RECORD
