Metadata-Version: 2.4
Name: ciso-genai
Version: 0.0.2
Summary: A framework for Causal Intelligence in Multi-Agent Generative AI.
Home-page: https://github.com/harshbopaliya/CISO-GENAI-Framework
Author: Harsh Bopaliya
Author-email: bopaliyaharsh7@gmail.com
License: MIT License
Classifier: Programming Language :: Python :: 3.10
Classifier: Programming Language :: Python :: 3.11
Classifier: Programming Language :: Python :: 3.12
Classifier: License :: OSI Approved :: MIT License
Classifier: Operating System :: OS Independent
Classifier: Intended Audience :: Science/Research
Classifier: Topic :: Scientific/Engineering :: Artificial Intelligence
Classifier: Topic :: Software Development :: Libraries :: Python Modules
Classifier: Development Status :: 2 - Pre-Alpha
Requires-Python: >=3.8
License-File: LICENSE
Requires-Dist: torch>=2.0.0
Requires-Dist: numpy>=1.26.0
Requires-Dist: gymnasium>=1.0.0
Requires-Dist: ripser>=0.6.12
Requires-Dist: PyYAML>=6.0.0
Dynamic: author
Dynamic: author-email
Dynamic: classifier
Dynamic: description
Dynamic: description-content-type
Dynamic: home-page
Dynamic: license
Dynamic: license-file
Dynamic: requires-dist
Dynamic: requires-python
Dynamic: summary
